enfig/__init__.py
enfig/base.py
enfig/bool_type.py
enfig/errors.py
enfig/py.typed
enfig-1.0.2.dist-info/METADATA
enfig-1.0.2.dist-info/WHEEL
enfig-1.0.2.dist-info/licenses/LICENSE
enfig-1.0.2.dist-info/RECORD
