Metadata-Version: 2.4
Name: enfig
Version: 1.0.2
Summary: Lean, zero dependency environment parsing library.
Project-URL: Source, https://github.com/datek/enfig
Author-email: Attila Dudás <attila.dudas@protonmail.com>
License-Expression: MIT
License-File: LICENSE
Requires-Python: >=3.9
